{
  "nodes": [
    {
      "id": "src/components/Modal/LoginPage.jsx",
      "label": "LoginPage",
      "routes": [
        "/login"
      ]
    },
    {
      "id": "src/components/ProtectedRoute.jsx",
      "label": "ProtectedRoute",
      "routes": [
        "/",
        "/dashboard",
        "/file-management",
        "/request",
        "/user-management",
        "/reports",
        "/settings"
      ],
      "isRoot": true
    }
  ],
  "edges": [
    {
      "id": "src\\components\\ProtectedRoute.jsx:10:11-to-src\\components\\Modal\\LoginPage.jsx",
      "source": "src\\components\\ProtectedRoute.jsx",
      "target": "src\\components\\Modal\\LoginPage.jsx",
      "data": {
        "viaRoute": "/login",
        "trigger": {
          "element": "<Navigate to=\"/login\" state={{ from: location }} replace />",
          "line": 10,
          "endLine": 10,
          "column": 11,
          "endColumn": 70,
          "sourceFile": "src\\components\\ProtectedRoute.jsx"
        }
      }
    },
    {
      "id": "src/components/ProtectedRoute.jsx:17:13-to-src/components/ProtectedRoute.jsx",
      "source": "src/components/ProtectedRoute.jsx",
      "target": "src/components/ProtectedRoute.jsx",
      "data": {
        "viaRoute": "/dashboard",
        "trigger": {
          "element": "<Navigate to=\"/dashboard\" replace />",
          "line": 17,
          "endLine": 17,
          "column": 13,
          "endColumn": 49,
          "sourceFile": "src/components/ProtectedRoute.jsx"
        }
      }
    }
  ]
}